therapy_planner/__init__.py
therapy_planner/bfgs.py
therapy_planner/costfunctions.py
therapy_planner/interface.py
therapy_planner/timer.py
therapy_planner/tests/__init__.py
therapy_planner/tests/test.map
therapy_planner/tests/test_bfgs.py
therapy_planner/tests/test_bounds.map
therapy_planner/tests/test_costfunctions.py
therapy_planner/tests/test_float.map
therapy_planner/tests/test_interface.py
therapy_planner/tests/test_invalid.map
therapy_planner/tests/test_max_violation.map
therapy_planner/tests/test_min_gt_max.map
therapy_planner/tests/test_min_gt_target.map
therapy_planner/tests/test_min_violation.map
therapy_planner/tests/test_missing_values.map
therapy_planner/tests/test_optimize.map
therapy_planner/tests/test_rotate.map
therapy_planner/tests/test_shape.map
therapy_planner/tests/test_target_gt_max.map
therapy_planner-1.0.0.dist-info/LICENSE
therapy_planner-1.0.0.dist-info/METADATA
therapy_planner-1.0.0.dist-info/WHEEL
therapy_planner-1.0.0.dist-info/top_level.txt
therapy_planner-1.0.0.dist-info/RECORD
