Metadata-Version: 2.1
Name: therapy-planner
Version: 1.0.0
Summary: A tool for dose optimization for Intensity Modulated Radiation Therapy (IMRT)
Home-page: https://github.com/DualSapiens/cs207-FinalProject
Author: DualSapiens
Author-email: 
License: UNKNOWN
Platform: UNKNOWN
Classifier: Programming Language :: Python :: 3
Classifier: License :: OSI Approved :: MIT License
Classifier: Operating System :: OS Independent
Requires-Dist: numpy
Requires-Dist: matplotlib
Requires-Dist: gradpy
